README.rst
setup.py
src/nblivereload/__init__.py
src/nblivereload/_version.py
src/nblivereload/serverextension.py
src/nblivereload.egg-info/PKG-INFO
src/nblivereload.egg-info/SOURCES.txt
src/nblivereload.egg-info/dependency_links.txt
src/nblivereload.egg-info/top_level.txt