Metadata-Version: 1.1
Name: nblivereload
Version: 0.1.0
Summary: Autoreload static files in the Jupyter Notebook
Home-page: https://github.com/bollwyvl/nb-livereload
Author: Nicholas Bollweg
Author-email: nbollweg@continuum.io
License: BSD-3-Clause
Keywords: ipython jupyter livereload
Platform: UNKNOWN
Classifier: Development Status :: 4 - Beta
Classifier: Framework :: IPython
Classifier: Programming Language :: Python
Classifier: License :: OSI Approved :: BSD License
